library_math/__init__.py
library_math/math.py
math_demo-0.0.1.dist-info/LICENSE
math_demo-0.0.1.dist-info/METADATA
math_demo-0.0.1.dist-info/WHEEL
math_demo-0.0.1.dist-info/top_level.txt
math_demo-0.0.1.dist-info/RECORD
